kurdish2image/__init__.py
kurdish2image/kurdish2image.py
kurdish2image/my-test.py
Kurdish2Image-0.0.7.dist-info/License.txt
Kurdish2Image-0.0.7.dist-info/METADATA
Kurdish2Image-0.0.7.dist-info/WHEEL
Kurdish2Image-0.0.7.dist-info/top_level.txt
Kurdish2Image-0.0.7.dist-info/RECORD
