Metadata-Version: 2.1
Name: Kurdish2Image
Version: 0.0.7
Summary: Create Kurdish style images from Text Based On Stable Diffusion Model
Home-page: https://github.com/falahgs/
Author: Falahgs.G.Saleih
Author-email: falahgs07@gmail.com
License: MIT
Keywords: StableDiffusion,CLIP,Transformers
Classifier: Programming Language :: Python :: 3
Classifier: License :: OSI Approved :: MIT License
Classifier: Operating System :: OS Independent
Requires-Python: >=3.6
License-File: License.txt
Requires-Dist: transformers
Requires-Dist: diffusion
Requires-Dist: diffusers
Requires-Dist: torch
Requires-Dist: accelerate
